{
    "boards": [
        { 
            "id": 1,
            "decks": [
                "longboard",
                "deck2",
                "deck3"
            ]
        },
        {
            "id": 2,
            "trucks": [
                "truck1",
                "truck2"
            ]
        },
        {
            "id": 3,
            "wheels": [
                "wheels1",
                "wheels2"
            ]
        },
        {
            "id": 4,
            "griptape": [
                true,
                false
            ]
        }
    ]
}   